milvus_haystack/__about__.py
milvus_haystack/__init__.py
milvus_haystack/document_store.py
milvus_haystack/filters.py
milvus_haystack/function.py
milvus_haystack/milvus_embedding_retriever.py
milvus_haystack/utils/__init__.py
milvus_haystack/utils/constant.py
milvus_haystack-0.0.18.dist-info/METADATA
milvus_haystack-0.0.18.dist-info/WHEEL
milvus_haystack-0.0.18.dist-info/licenses/LICENSE.txt
milvus_haystack-0.0.18.dist-info/RECORD
