Metadata-Version: 2.4
Name: milvus-haystack
Version: 0.0.18
Project-URL: Documentation, https://github.com/milvus-io/milvus-haystack#readme
Project-URL: Issues, https://github.com/milvus-io/milvus-haystack/issues
Project-URL: Source, https://github.com/milvus-io/milvus-haystack
Author-email: Zilliz <support@zilliz.com>
License-Expression: Apache-2.0
License-File: LICENSE.txt
Classifier: Development Status :: 4 - Beta
Classifier: Programming Language :: Python
Classifier: Programming Language :: Python :: 3.8
Classifier: Programming Language :: Python :: 3.9
Classifier: Programming Language :: Python :: 3.10
Classifier: Programming Language :: Python :: 3.11
Classifier: Programming Language :: Python :: Implementation :: CPython
Classifier: Programming Language :: Python :: Implementation :: PyPy
Requires-Python: >=3.8
Requires-Dist: haystack-ai
Requires-Dist: pymilvus>=2.5.6
Requires-Dist: typing-extensions
